{
    "market": {
        "symbol": "XRP/USDT:USDT",
        "timeframe": "1h",
        "htf": "4h"
    },
    "strategy": {
        "type": "physics",
        "enable_vwap_setup": true,
        "enable_impulse_pullback": true,
        "enable_volatility_expansion": true,
        "atr_period": 10,
        "atr_multiplier_trend": 1.61,
        "momentum_period": 13,
        "momentum_sma_period": 3,
        "volume_ma_period": 10,
        "volume_threshold": 1.55,
        "regime_atr_threshold": 0.0137,
        "ema_fast": 38,
        "ema_slow": 48,
        "range_lookback": 25,
        "range_overlap_threshold": 0.65,
        "vwap_mean_reversion_threshold": 1.06,
        "momentum_threshold": 0.94,
        "sl_atr_multiplier": 1.04,
        "tp_atr_multiplier": 1.84,
        "tp_atr_multiplier_expansion": 3.31,
        "exit_on_regime_change": true,
        "exit_on_momentum_reversal": true,
        "exit_on_vwap_cross": false,
        "exit_on_energy_loss": true,
        "supertrend_atr_period": 14,
        "supertrend_multiplier": 3.4
    },
    "risk": {
        "margin_mode": "isolated",
        "risk_per_trade_pct": 1.9,
        "risk_reward_ratio": 1.77,
        "leverage": 9,
        "trailing_stop_activation_rr": 1.23,
        "trailing_stop_callback_rate_pct": 0.41,
        "atr_multiplier_sl": 2.13,
        "min_sl_pct": 0.5
    }
}